labstack/__init__.py
labstack/client.py
labstack/currency.py
labstack/domain.py
labstack/email.py
labstack/ip.py
labstack/test_currency.py
labstack/test_domain.py
labstack/test_email.py
labstack/test_ip.py
labstack/test_webpage.py
labstack/util.py
labstack/webpage.py
labstack-1.0.1.dist-info/LICENSE
labstack-1.0.1.dist-info/METADATA
labstack-1.0.1.dist-info/WHEEL
labstack-1.0.1.dist-info/top_level.txt
labstack-1.0.1.dist-info/RECORD
