Metadata-Version: 2.1
Name: labstack
Version: 1.0.1
Summary: Official Python client library for the LabStack API
Home-page: https://github.com/labstack/labstack-python
Author: Vishal Rana
Author-email: vr@labstack.com
License: MIT
Keywords: image compress,image resize,text summary,barcode generate,barcode scan
Platform: UNKNOWN
Classifier: Programming Language :: Python :: 3.6
Classifier: Programming Language :: Python :: 3.7
Classifier: Programming Language :: Python :: 3.8
Requires-Dist: requests (==2.22.0)
